django_fake_model/__init__.py
django_fake_model/case_extension.py
django_fake_model/models.py
django_fake_model-0.1.4.dist-info/DESCRIPTION.rst
django_fake_model-0.1.4.dist-info/METADATA
django_fake_model-0.1.4.dist-info/metadata.json
django_fake_model-0.1.4.dist-info/RECORD
django_fake_model-0.1.4.dist-info/top_level.txt
django_fake_model-0.1.4.dist-info/WHEEL
