Metadata-Version: 2.0
Name: django-fake-model
Version: 0.1.4
Summary: Simple library for creating fake models in the unit tests.
Home-page: https://github.com/erm0l0v/django-fake-model
Author: Kirill Ermolov
Author-email: erm0l0v@ya.ru
License: BSD
Keywords: django-fake-model
Platform: UNKNOWN
Classifier: Development Status :: 3 - Alpha
Classifier: Framework :: Django
Classifier: Intended Audience :: Developers
Classifier: License :: OSI Approved :: BSD License
Classifier: Natural Language :: English
Classifier: Programming Language :: Python :: 2
Classifier: Programming Language :: Python :: 2.7
Classifier: Programming Language :: Python :: 3
Classifier: Programming Language :: Python :: 3.3
Classifier: Programming Language :: Python :: 3.4
